README.md
setup.cfg
setup.py
src/speech_analysis_tools.egg-info/PKG-INFO
src/speech_analysis_tools.egg-info/SOURCES.txt
src/speech_analysis_tools.egg-info/dependency_links.txt
src/speech_analysis_tools.egg-info/requires.txt
src/speech_analysis_tools.egg-info/top_level.txt
src/speechtools/__init__.py
src/speechtools/audio_utils.py
src/speechtools/features.py
src/speechtools/lpc_residuals.py
src/speechtools/srh.py