Metadata-Version: 2.1
Name: speech-analysis-tools
Version: 0.1.2
Summary: Vocal Fry and other Metrics
Home-page: https://github.com/resemble-ai/speech-analysis-tools
Author: AdityaTB, Zihan Jin
Author-email: aditya@resemble.ai
License: MIT
Download-URL: https://github.com/resemble-ai/speech-analysis-tools/archive/refs/tags/v0.1.2.tar.gz
Project-URL: Bug Reports, https://github.com/resemble-ai/speech-analysis-tools/issues
Project-URL: Source, https://github.com/resemble-ai/speech-analysis-tools/src/
Keywords: Kane Drugman,Vocal Fry,Creaky Voice,Speech Analysis
Platform: UNKNOWN
Requires-Python: >=3.6
